Metadata-Version: 1.1
Name: filemerge
Version: 0.0.3
Summary: Filemerge: Tool to merge small HDFS files
Home-page: https://github.com/intuit/filemerge
Author: Rohan Kekatpure
Author-email: rohan_kekatpure@intuit.com
License: UNKNOWN
Download-URL: https://github.com/intuit/filemerge/tarball/0.1
Keywords: pypi,filemerge
Platform: UNKNOWN
